olivepy.py
olivepy-0.0.1.dist-info/licenses/LICENSE
olivepy-0.0.1.dist-info/METADATA
olivepy-0.0.1.dist-info/WHEEL
olivepy-0.0.1.dist-info/entry_points.txt
olivepy-0.0.1.dist-info/top_level.txt
olivepy-0.0.1.dist-info/RECORD
