Metadata-Version: 2.4
Name: olivepy
Version: 0.0.1
Summary: A python inliner tool for shell script
Author: Alexandros Andreou
License-Expression: MIT
Project-URL: Homepage, https://github.com/alex10791/olivepy
Project-URL: Issues, https://github.com/alex10791/olivepy/issues
Classifier: Programming Language :: Python :: 3
Classifier: Operating System :: OS Independent
Requires-Python: >=3.8
License-File: LICENSE
Dynamic: license-file
